[
  {
    "line": 2,
    "elements": [
      {
        "start_timestamp": "2021-11-06T08:10:28.561Z",
        "before": [
          {
            "result": {
              "duration": 7106100,
              "status": "passed"
            },
            "match": {
              "location": "stepdefinitions.Hooks.setUp()"
            }
          }
        ],
        "line": 13,
        "name": "login_with_manager_credentials",
        "description": "",
        "id": "login-functionality-with-right-credentials;login-with-manager-credentials;manager-data;2",
        "after": [
          {
            "result": {
              "error_message": "java.lang.NoClassDefFoundError: Could not initialize class io.github.bonigarcia.wdm.WebDriverManager\r\n\tat utilities.Driver.getDriver(Driver.java:17)\r\n\tat stepdefinitions.Hooks.tearDown(Hooks.java:23)\r\n",
              "duration": 2632200,
              "status": "failed"
            },
            "match": {
              "location": "stepdefinitions.Hooks.tearDown(io.cucumber.java.Scenario)"
            }
          }
        ],
        "type": "scenario",
        "keyword": "Scenario Outline",
        "steps": [
          {
            "result": {
              "error_message": "io.cucumber.core.exception.CucumberException: Failed to instantiate class stepdefinitions.Day19_Login_Step_Definitions\r\n\tat io.cucumber.core.runtime.ObjectFactoryServiceLoader$DefaultJavaObjectFactory.cacheNewInstance(ObjectFactoryServiceLoader.java:149)\r\n\tat io.cucumber.core.runtime.ObjectFactoryServiceLoader$DefaultJavaObjectFactory.getInstance(ObjectFactoryServiceLoader.java:133)\r\n\tat io.cucumber.java.AbstractGlueDefinition.invokeMethod(AbstractGlueDefinition.java:47)\r\n\tat io.cucumber.java.JavaStepDefinition.execute(JavaStepDefinition.java:29)\r\n\tat io.cucumber.core.runner.CoreStepDefinition.execute(CoreStepDefinition.java:66)\r\n\tat io.cucumber.core.runner.PickleStepDefinitionMatch.runStep(PickleStepDefinitionMatch.java:63)\r\n\tat io.cucumber.core.runner.ExecutionMode$1.execute(ExecutionMode.java:10)\r\n\tat io.cucumber.core.runner.TestStep.executeStep(TestStep.java:92)\r\n\tat io.cucumber.core.runner.TestStep.run(TestStep.java:64)\r\n\tat io.cucumber.core.runner.PickleStepTestStep.run(PickleStepTestStep.java:51)\r\n\tat io.cucumber.core.runner.TestCase.run(TestCase.java:104)\r\n\tat io.cucumber.core.runner.Runner.runPickle(Runner.java:73)\r\n\tat io.cucumber.junit.PickleRunners$NoStepDescriptions.run(PickleRunners.java:151)\r\n\tat io.cucumber.junit.FeatureRunner.runChild(FeatureRunner.java:135)\r\n\tat io.cucumber.junit.FeatureRunner.runChild(FeatureRunner.java:27)\r\n\tat org.junit.runners.ParentRunner$4.run(ParentRunner.java:331)\r\n\tat org.junit.runners.ParentRunner$1.schedule(ParentRunner.java:79)\r\n\tat org.junit.runners.ParentRunner.runChildren(ParentRunner.java:329)\r\n\tat org.junit.runners.ParentRunner.access$100(ParentRunner.java:66)\r\n\tat org.junit.runners.ParentRunner$2.evaluate(ParentRunner.java:293)\r\n\tat org.junit.runners.ParentRunner$3.evaluate(ParentRunner.java:306)\r\n\tat org.junit.runners.ParentRunner.run(ParentRunner.java:413)\r\n\tat io.cucumber.junit.Cucumber.runChild(Cucumber.java:200)\r\n\tat io.cucumber.junit.Cucumber.runChild(Cucumber.java:90)\r\n\tat org.junit.runners.ParentRunner$4.run(ParentRunner.java:331)\r\n\tat org.junit.runners.ParentRunner$1.schedule(ParentRunner.java:79)\r\n\tat org.junit.runners.ParentRunner.runChildren(ParentRunner.java:329)\r\n\tat org.junit.runners.ParentRunner.access$100(ParentRunner.java:66)\r\n\tat org.junit.runners.ParentRunner$2.evaluate(ParentRunner.java:293)\r\n\tat io.cucumber.junit.Cucumber$RunCucumber.evaluate(Cucumber.java:235)\r\n\tat org.junit.runners.ParentRunner$3.evaluate(ParentRunner.java:306)\r\n\tat org.junit.runners.ParentRunner.run(ParentRunner.java:413)\r\n\tat org.junit.runner.JUnitCore.run(JUnitCore.java:137)\r\n\tat com.intellij.junit4.JUnit4IdeaTestRunner.startRunnerWithArgs(JUnit4IdeaTestRunner.java:69)\r\n\tat com.intellij.rt.junit.IdeaTestRunner$Repeater.startRunnerWithArgs(IdeaTestRunner.java:33)\r\n\tat com.intellij.rt.junit.JUnitStarter.prepareStreamsAndStart(JUnitStarter.java:235)\r\n\tat com.intellij.rt.junit.JUnitStarter.main(JUnitStarter.java:54)\r\nCaused by: java.lang.reflect.InvocationTargetException\r\n\tat java.base/jdk.internal.reflect.NativeConstructorAccessorImpl.newInstance0(Native Method)\r\n\tat java.base/jdk.internal.reflect.NativeConstructorAccessorImpl.newInstance(NativeConstructorAccessorImpl.java:62)\r\n\tat java.base/jdk.internal.reflect.DelegatingConstructorAccessorImpl.newInstance(DelegatingConstructorAccessorImpl.java:45)\r\n\tat java.base/java.lang.reflect.Constructor.newInstance(Constructor.java:490)\r\n\tat io.cucumber.core.runtime.ObjectFactoryServiceLoader$DefaultJavaObjectFactory.cacheNewInstance(ObjectFactoryServiceLoader.java:141)\r\n\t... 36 more\r\nCaused by: java.lang.NoSuchMethodError: org.slf4j.impl.StaticLoggerBinder.getSingleton()Lorg/slf4j/impl/StaticLoggerBinder;\r\n\tat org.slf4j.LoggerFactory.bind(LoggerFactory.java:150)\r\n\tat org.slf4j.LoggerFactory.performInitialization(LoggerFactory.java:124)\r\n\tat org.slf4j.LoggerFactory.getILoggerFactory(LoggerFactory.java:417)\r\n\tat org.slf4j.LoggerFactory.getLogger(LoggerFactory.java:362)\r\n\tat org.slf4j.LoggerFactory.getLogger(LoggerFactory.java:388)\r\n\tat io.github.bonigarcia.wdm.WebDriverManager.\u003cclinit\u003e(WebDriverManager.java:136)\r\n\tat utilities.Driver.getDriver(Driver.java:17)\r\n\tat pages.LoginPage.\u003cinit\u003e(LoginPage.java:9)\r\n\tat stepdefinitions.Day19_Login_Step_Definitions.\u003cinit\u003e(Day19_Login_Step_Definitions.java:15)\r\n\t... 41 more\r\n",
              "duration": 50606900,
              "status": "failed"
            },
            "line": 5,
            "name": "user is on the application page",
            "match": {
              "location": "stepdefinitions.Day19_Login_Step_Definitions.user_is_on_the_application_page()"
            },
            "keyword": "Given "
          },
          {
            "result": {
              "status": "skipped"
            },
            "line": 6,
            "name": "user enters manager id \"manager\"",
            "match": {
              "arguments": [
                {
                  "val": "\"manager\"",
                  "offset": 23
                }
              ],
              "location": "stepdefinitions.Day19_Login_Step_Definitions.user_enters_manager_id(java.lang.String)"
            },
            "keyword": "And "
          },
          {
            "result": {
              "status": "skipped"
            },
            "line": 7,
            "name": "user enters manager password \"Manager1!\"",
            "match": {
              "arguments": [
                {
                  "val": "\"Manager1!\"",
                  "offset": 29
                }
              ],
              "location": "stepdefinitions.Day19_Login_Step_Definitions.user_enters_manager_password(java.lang.String)"
            },
            "keyword": "And "
          },
          {
            "result": {
              "status": "skipped"
            },
            "line": 8,
            "name": "user clicks on the login button",
            "match": {
              "location": "stepdefinitions.Day19_Login_Step_Definitions.user_clicks_on_the_login_button()"
            },
            "keyword": "When "
          },
          {
            "result": {
              "status": "skipped"
            },
            "line": 9,
            "name": "verify the \"manager\" is displayed",
            "match": {
              "arguments": [
                {
                  "val": "\"manager\"",
                  "offset": 11
                }
              ],
              "location": "stepdefinitions.Day19_Login_Step_Definitions.verify_the_is_displayed(java.lang.String)"
            },
            "keyword": "Then "
          },
          {
            "result": {
              "duration": 361500,
              "status": "skipped"
            },
            "line": 10,
            "name": "close the application",
            "match": {
              "location": "stepdefinitions.Day17_GoogleSearchStepDefinitions.close_the_application()"
            },
            "keyword": "Then "
          }
        ],
        "tags": [
          {
            "name": "@login_test"
          },
          {
            "name": "@manager_login_test"
          }
        ]
      },
      {
        "start_timestamp": "2021-11-06T08:10:28.925Z",
        "before": [
          {
            "result": {
              "duration": 998600,
              "status": "passed"
            },
            "match": {
              "location": "stepdefinitions.Hooks.setUp()"
            }
          }
        ],
        "line": 14,
        "name": "login_with_manager_credentials",
        "description": "",
        "id": "login-functionality-with-right-credentials;login-with-manager-credentials;manager-data;3",
        "after": [
          {
            "result": {
              "error_message": "java.lang.NoClassDefFoundError: Could not initialize class io.github.bonigarcia.wdm.WebDriverManager\r\n\tat utilities.Driver.getDriver(Driver.java:17)\r\n\tat stepdefinitions.Hooks.tearDown(Hooks.java:23)\r\n",
              "duration": 19768000,
              "status": "failed"
            },
            "match": {
              "location": "stepdefinitions.Hooks.tearDown(io.cucumber.java.Scenario)"
            }
          }
        ],
        "type": "scenario",
        "keyword": "Scenario Outline",
        "steps": [
          {
            "result": {
              "error_message": "io.cucumber.core.exception.CucumberException: Failed to instantiate class stepdefinitions.Day19_Login_Step_Definitions\r\n\tat io.cucumber.core.runtime.ObjectFactoryServiceLoader$DefaultJavaObjectFactory.cacheNewInstance(ObjectFactoryServiceLoader.java:149)\r\n\tat io.cucumber.core.runtime.ObjectFactoryServiceLoader$DefaultJavaObjectFactory.getInstance(ObjectFactoryServiceLoader.java:133)\r\n\tat io.cucumber.java.AbstractGlueDefinition.invokeMethod(AbstractGlueDefinition.java:47)\r\n\tat io.cucumber.java.JavaStepDefinition.execute(JavaStepDefinition.java:29)\r\n\tat io.cucumber.core.runner.CoreStepDefinition.execute(CoreStepDefinition.java:66)\r\n\tat io.cucumber.core.runner.PickleStepDefinitionMatch.runStep(PickleStepDefinitionMatch.java:63)\r\n\tat io.cucumber.core.runner.ExecutionMode$1.execute(ExecutionMode.java:10)\r\n\tat io.cucumber.core.runner.TestStep.executeStep(TestStep.java:92)\r\n\tat io.cucumber.core.runner.TestStep.run(TestStep.java:64)\r\n\tat io.cucumber.core.runner.PickleStepTestStep.run(PickleStepTestStep.java:51)\r\n\tat io.cucumber.core.runner.TestCase.run(TestCase.java:104)\r\n\tat io.cucumber.core.runner.Runner.runPickle(Runner.java:73)\r\n\tat io.cucumber.junit.PickleRunners$NoStepDescriptions.run(PickleRunners.java:151)\r\n\tat io.cucumber.junit.FeatureRunner.runChild(FeatureRunner.java:135)\r\n\tat io.cucumber.junit.FeatureRunner.runChild(FeatureRunner.java:27)\r\n\tat org.junit.runners.ParentRunner$4.run(ParentRunner.java:331)\r\n\tat org.junit.runners.ParentRunner$1.schedule(ParentRunner.java:79)\r\n\tat org.junit.runners.ParentRunner.runChildren(ParentRunner.java:329)\r\n\tat org.junit.runners.ParentRunner.access$100(ParentRunner.java:66)\r\n\tat org.junit.runners.ParentRunner$2.evaluate(ParentRunner.java:293)\r\n\tat org.junit.runners.ParentRunner$3.evaluate(ParentRunner.java:306)\r\n\tat org.junit.runners.ParentRunner.run(ParentRunner.java:413)\r\n\tat io.cucumber.junit.Cucumber.runChild(Cucumber.java:200)\r\n\tat io.cucumber.junit.Cucumber.runChild(Cucumber.java:90)\r\n\tat org.junit.runners.ParentRunner$4.run(ParentRunner.java:331)\r\n\tat org.junit.runners.ParentRunner$1.schedule(ParentRunner.java:79)\r\n\tat org.junit.runners.ParentRunner.runChildren(ParentRunner.java:329)\r\n\tat org.junit.runners.ParentRunner.access$100(ParentRunner.java:66)\r\n\tat org.junit.runners.ParentRunner$2.evaluate(ParentRunner.java:293)\r\n\tat io.cucumber.junit.Cucumber$RunCucumber.evaluate(Cucumber.java:235)\r\n\tat org.junit.runners.ParentRunner$3.evaluate(ParentRunner.java:306)\r\n\tat org.junit.runners.ParentRunner.run(ParentRunner.java:413)\r\n\tat org.junit.runner.JUnitCore.run(JUnitCore.java:137)\r\n\tat com.intellij.junit4.JUnit4IdeaTestRunner.startRunnerWithArgs(JUnit4IdeaTestRunner.java:69)\r\n\tat com.intellij.rt.junit.IdeaTestRunner$Repeater.startRunnerWithArgs(IdeaTestRunner.java:33)\r\n\tat com.intellij.rt.junit.JUnitStarter.prepareStreamsAndStart(JUnitStarter.java:235)\r\n\tat com.intellij.rt.junit.JUnitStarter.main(JUnitStarter.java:54)\r\nCaused by: java.lang.reflect.InvocationTargetException\r\n\tat java.base/jdk.internal.reflect.NativeConstructorAccessorImpl.newInstance0(Native Method)\r\n\tat java.base/jdk.internal.reflect.NativeConstructorAccessorImpl.newInstance(NativeConstructorAccessorImpl.java:62)\r\n\tat java.base/jdk.internal.reflect.DelegatingConstructorAccessorImpl.newInstance(DelegatingConstructorAccessorImpl.java:45)\r\n\tat java.base/java.lang.reflect.Constructor.newInstance(Constructor.java:490)\r\n\tat io.cucumber.core.runtime.ObjectFactoryServiceLoader$DefaultJavaObjectFactory.cacheNewInstance(ObjectFactoryServiceLoader.java:141)\r\n\t... 36 more\r\nCaused by: java.lang.NoClassDefFoundError: Could not initialize class io.github.bonigarcia.wdm.WebDriverManager\r\n\tat utilities.Driver.getDriver(Driver.java:17)\r\n\tat pages.LoginPage.\u003cinit\u003e(LoginPage.java:9)\r\n\tat stepdefinitions.Day19_Login_Step_Definitions.\u003cinit\u003e(Day19_Login_Step_Definitions.java:15)\r\n\t... 41 more\r\n",
              "duration": 1000200,
              "status": "failed"
            },
            "line": 5,
            "name": "user is on the application page",
            "match": {
              "location": "stepdefinitions.Day19_Login_Step_Definitions.user_is_on_the_application_page()"
            },
            "keyword": "Given "
          },
          {
            "result": {
              "status": "skipped"
            },
            "line": 6,
            "name": "user enters manager id \"manager2\"",
            "match": {
              "arguments": [
                {
                  "val": "\"manager2\"",
                  "offset": 23
                }
              ],
              "location": "stepdefinitions.Day19_Login_Step_Definitions.user_enters_manager_id(java.lang.String)"
            },
            "keyword": "And "
          },
          {
            "result": {
              "status": "skipped"
            },
            "line": 7,
            "name": "user enters manager password \"Manager2!\"",
            "match": {
              "arguments": [
                {
                  "val": "\"Manager2!\"",
                  "offset": 29
                }
              ],
              "location": "stepdefinitions.Day19_Login_Step_Definitions.user_enters_manager_password(java.lang.String)"
            },
            "keyword": "And "
          },
          {
            "result": {
              "status": "skipped"
            },
            "line": 8,
            "name": "user clicks on the login button",
            "match": {
              "location": "stepdefinitions.Day19_Login_Step_Definitions.user_clicks_on_the_login_button()"
            },
            "keyword": "When "
          },
          {
            "result": {
              "duration": 2995400,
              "status": "skipped"
            },
            "line": 9,
            "name": "verify the \"manager2\" is displayed",
            "match": {
              "arguments": [
                {
                  "val": "\"manager2\"",
                  "offset": 11
                }
              ],
              "location": "stepdefinitions.Day19_Login_Step_Definitions.verify_the_is_displayed(java.lang.String)"
            },
            "keyword": "Then "
          },
          {
            "result": {
              "status": "skipped"
            },
            "line": 10,
            "name": "close the application",
            "match": {
              "location": "stepdefinitions.Day17_GoogleSearchStepDefinitions.close_the_application()"
            },
            "keyword": "Then "
          }
        ],
        "tags": [
          {
            "name": "@login_test"
          },
          {
            "name": "@manager_login_test"
          }
        ]
      },
      {
        "start_timestamp": "2021-11-06T08:10:29.063Z",
        "before": [
          {
            "result": {
              "status": "passed"
            },
            "match": {
              "location": "stepdefinitions.Hooks.setUp()"
            }
          }
        ],
        "line": 15,
        "name": "login_with_manager_credentials",
        "description": "",
        "id": "login-functionality-with-right-credentials;login-with-manager-credentials;manager-data;4",
        "after": [
          {
            "result": {
              "error_message": "java.lang.NoClassDefFoundError: Could not initialize class io.github.bonigarcia.wdm.WebDriverManager\r\n\tat utilities.Driver.getDriver(Driver.java:17)\r\n\tat stepdefinitions.Hooks.tearDown(Hooks.java:23)\r\n",
              "status": "failed"
            },
            "match": {
              "location": "stepdefinitions.Hooks.tearDown(io.cucumber.java.Scenario)"
            }
          }
        ],
        "type": "scenario",
        "keyword": "Scenario Outline",
        "steps": [
          {
            "result": {
              "error_message": "io.cucumber.core.exception.CucumberException: Failed to instantiate class stepdefinitions.Day19_Login_Step_Definitions\r\n\tat io.cucumber.core.runtime.ObjectFactoryServiceLoader$DefaultJavaObjectFactory.cacheNewInstance(ObjectFactoryServiceLoader.java:149)\r\n\tat io.cucumber.core.runtime.ObjectFactoryServiceLoader$DefaultJavaObjectFactory.getInstance(ObjectFactoryServiceLoader.java:133)\r\n\tat io.cucumber.java.AbstractGlueDefinition.invokeMethod(AbstractGlueDefinition.java:47)\r\n\tat io.cucumber.java.JavaStepDefinition.execute(JavaStepDefinition.java:29)\r\n\tat io.cucumber.core.runner.CoreStepDefinition.execute(CoreStepDefinition.java:66)\r\n\tat io.cucumber.core.runner.PickleStepDefinitionMatch.runStep(PickleStepDefinitionMatch.java:63)\r\n\tat io.cucumber.core.runner.ExecutionMode$1.execute(ExecutionMode.java:10)\r\n\tat io.cucumber.core.runner.TestStep.executeStep(TestStep.java:92)\r\n\tat io.cucumber.core.runner.TestStep.run(TestStep.java:64)\r\n\tat io.cucumber.core.runner.PickleStepTestStep.run(PickleStepTestStep.java:51)\r\n\tat io.cucumber.core.runner.TestCase.run(TestCase.java:104)\r\n\tat io.cucumber.core.runner.Runner.runPickle(Runner.java:73)\r\n\tat io.cucumber.junit.PickleRunners$NoStepDescriptions.run(PickleRunners.java:151)\r\n\tat io.cucumber.junit.FeatureRunner.runChild(FeatureRunner.java:135)\r\n\tat io.cucumber.junit.FeatureRunner.runChild(FeatureRunner.java:27)\r\n\tat org.junit.runners.ParentRunner$4.run(ParentRunner.java:331)\r\n\tat org.junit.runners.ParentRunner$1.schedule(ParentRunner.java:79)\r\n\tat org.junit.runners.ParentRunner.runChildren(ParentRunner.java:329)\r\n\tat org.junit.runners.ParentRunner.access$100(ParentRunner.java:66)\r\n\tat org.junit.runners.ParentRunner$2.evaluate(ParentRunner.java:293)\r\n\tat org.junit.runners.ParentRunner$3.evaluate(ParentRunner.java:306)\r\n\tat org.junit.runners.ParentRunner.run(ParentRunner.java:413)\r\n\tat io.cucumber.junit.Cucumber.runChild(Cucumber.java:200)\r\n\tat io.cucumber.junit.Cucumber.runChild(Cucumber.java:90)\r\n\tat org.junit.runners.ParentRunner$4.run(ParentRunner.java:331)\r\n\tat org.junit.runners.ParentRunner$1.schedule(ParentRunner.java:79)\r\n\tat org.junit.runners.ParentRunner.runChildren(ParentRunner.java:329)\r\n\tat org.junit.runners.ParentRunner.access$100(ParentRunner.java:66)\r\n\tat org.junit.runners.ParentRunner$2.evaluate(ParentRunner.java:293)\r\n\tat io.cucumber.junit.Cucumber$RunCucumber.evaluate(Cucumber.java:235)\r\n\tat org.junit.runners.ParentRunner$3.evaluate(ParentRunner.java:306)\r\n\tat org.junit.runners.ParentRunner.run(ParentRunner.java:413)\r\n\tat org.junit.runner.JUnitCore.run(JUnitCore.java:137)\r\n\tat com.intellij.junit4.JUnit4IdeaTestRunner.startRunnerWithArgs(JUnit4IdeaTestRunner.java:69)\r\n\tat com.intellij.rt.junit.IdeaTestRunner$Repeater.startRunnerWithArgs(IdeaTestRunner.java:33)\r\n\tat com.intellij.rt.junit.JUnitStarter.prepareStreamsAndStart(JUnitStarter.java:235)\r\n\tat com.intellij.rt.junit.JUnitStarter.main(JUnitStarter.java:54)\r\nCaused by: java.lang.reflect.InvocationTargetException\r\n\tat java.base/jdk.internal.reflect.NativeConstructorAccessorImpl.newInstance0(Native Method)\r\n\tat java.base/jdk.internal.reflect.NativeConstructorAccessorImpl.newInstance(NativeConstructorAccessorImpl.java:62)\r\n\tat java.base/jdk.internal.reflect.DelegatingConstructorAccessorImpl.newInstance(DelegatingConstructorAccessorImpl.java:45)\r\n\tat java.base/java.lang.reflect.Constructor.newInstance(Constructor.java:490)\r\n\tat io.cucumber.core.runtime.ObjectFactoryServiceLoader$DefaultJavaObjectFactory.cacheNewInstance(ObjectFactoryServiceLoader.java:141)\r\n\t... 36 more\r\nCaused by: java.lang.NoClassDefFoundError: Could not initialize class io.github.bonigarcia.wdm.WebDriverManager\r\n\tat utilities.Driver.getDriver(Driver.java:17)\r\n\tat pages.LoginPage.\u003cinit\u003e(LoginPage.java:9)\r\n\tat stepdefinitions.Day19_Login_Step_Definitions.\u003cinit\u003e(Day19_Login_Step_Definitions.java:15)\r\n\t... 41 more\r\n",
              "duration": 999900,
              "status": "failed"
            },
            "line": 5,
            "name": "user is on the application page",
            "match": {
              "location": "stepdefinitions.Day19_Login_Step_Definitions.user_is_on_the_application_page()"
            },
            "keyword": "Given "
          },
          {
            "result": {
              "duration": 1002700,
              "status": "skipped"
            },
            "line": 6,
            "name": "user enters manager id \"manager3\"",
            "match": {
              "arguments": [
                {
                  "val": "\"manager3\"",
                  "offset": 23
                }
              ],
              "location": "stepdefinitions.Day19_Login_Step_Definitions.user_enters_manager_id(java.lang.String)"
            },
            "keyword": "And "
          },
          {
            "result": {
              "duration": 998000,
              "status": "skipped"
            },
            "line": 7,
            "name": "user enters manager password \"Manager3!\"",
            "match": {
              "arguments": [
                {
                  "val": "\"Manager3!\"",
                  "offset": 29
                }
              ],
              "location": "stepdefinitions.Day19_Login_Step_Definitions.user_enters_manager_password(java.lang.String)"
            },
            "keyword": "And "
          },
          {
            "result": {
              "status": "skipped"
            },
            "line": 8,
            "name": "user clicks on the login button",
            "match": {
              "location": "stepdefinitions.Day19_Login_Step_Definitions.user_clicks_on_the_login_button()"
            },
            "keyword": "When "
          },
          {
            "result": {
              "status": "skipped"
            },
            "line": 9,
            "name": "verify the \"manager3\" is displayed",
            "match": {
              "arguments": [
                {
                  "val": "\"manager3\"",
                  "offset": 11
                }
              ],
              "location": "stepdefinitions.Day19_Login_Step_Definitions.verify_the_is_displayed(java.lang.String)"
            },
            "keyword": "Then "
          },
          {
            "result": {
              "status": "skipped"
            },
            "line": 10,
            "name": "close the application",
            "match": {
              "location": "stepdefinitions.Day17_GoogleSearchStepDefinitions.close_the_application()"
            },
            "keyword": "Then "
          }
        ],
        "tags": [
          {
            "name": "@login_test"
          },
          {
            "name": "@manager_login_test"
          }
        ]
      },
      {
        "start_timestamp": "2021-11-06T08:10:29.181Z",
        "before": [
          {
            "result": {
              "status": "passed"
            },
            "match": {
              "location": "stepdefinitions.Hooks.setUp()"
            }
          }
        ],
        "line": 35,
        "name": "login_with_admin_credentials",
        "description": "",
        "id": "login-functionality-with-right-credentials;login-with-admin-credentials;admin-data;2",
        "after": [
          {
            "result": {
              "error_message": "java.lang.NoClassDefFoundError: Could not initialize class io.github.bonigarcia.wdm.WebDriverManager\r\n\tat utilities.Driver.getDriver(Driver.java:17)\r\n\tat stepdefinitions.Hooks.tearDown(Hooks.java:23)\r\n",
              "duration": 995700,
              "status": "failed"
            },
            "match": {
              "location": "stepdefinitions.Hooks.tearDown(io.cucumber.java.Scenario)"
            }
          }
        ],
        "type": "scenario",
        "keyword": "Scenario Outline",
        "steps": [
          {
            "result": {
              "error_message": "io.cucumber.core.exception.CucumberException: Failed to instantiate class stepdefinitions.Day19_Login_Step_Definitions\r\n\tat io.cucumber.core.runtime.ObjectFactoryServiceLoader$DefaultJavaObjectFactory.cacheNewInstance(ObjectFactoryServiceLoader.java:149)\r\n\tat io.cucumber.core.runtime.ObjectFactoryServiceLoader$DefaultJavaObjectFactory.getInstance(ObjectFactoryServiceLoader.java:133)\r\n\tat io.cucumber.java.AbstractGlueDefinition.invokeMethod(AbstractGlueDefinition.java:47)\r\n\tat io.cucumber.java.JavaStepDefinition.execute(JavaStepDefinition.java:29)\r\n\tat io.cucumber.core.runner.CoreStepDefinition.execute(CoreStepDefinition.java:66)\r\n\tat io.cucumber.core.runner.PickleStepDefinitionMatch.runStep(PickleStepDefinitionMatch.java:63)\r\n\tat io.cucumber.core.runner.ExecutionMode$1.execute(ExecutionMode.java:10)\r\n\tat io.cucumber.core.runner.TestStep.executeStep(TestStep.java:92)\r\n\tat io.cucumber.core.runner.TestStep.run(TestStep.java:64)\r\n\tat io.cucumber.core.runner.PickleStepTestStep.run(PickleStepTestStep.java:51)\r\n\tat io.cucumber.core.runner.TestCase.run(TestCase.java:104)\r\n\tat io.cucumber.core.runner.Runner.runPickle(Runner.java:73)\r\n\tat io.cucumber.junit.PickleRunners$NoStepDescriptions.run(PickleRunners.java:151)\r\n\tat io.cucumber.junit.FeatureRunner.runChild(FeatureRunner.java:135)\r\n\tat io.cucumber.junit.FeatureRunner.runChild(FeatureRunner.java:27)\r\n\tat org.junit.runners.ParentRunner$4.run(ParentRunner.java:331)\r\n\tat org.junit.runners.ParentRunner$1.schedule(ParentRunner.java:79)\r\n\tat org.junit.runners.ParentRunner.runChildren(ParentRunner.java:329)\r\n\tat org.junit.runners.ParentRunner.access$100(ParentRunner.java:66)\r\n\tat org.junit.runners.ParentRunner$2.evaluate(ParentRunner.java:293)\r\n\tat org.junit.runners.ParentRunner$3.evaluate(ParentRunner.java:306)\r\n\tat org.junit.runners.ParentRunner.run(ParentRunner.java:413)\r\n\tat io.cucumber.junit.Cucumber.runChild(Cucumber.java:200)\r\n\tat io.cucumber.junit.Cucumber.runChild(Cucumber.java:90)\r\n\tat org.junit.runners.ParentRunner$4.run(ParentRunner.java:331)\r\n\tat org.junit.runners.ParentRunner$1.schedule(ParentRunner.java:79)\r\n\tat org.junit.runners.ParentRunner.runChildren(ParentRunner.java:329)\r\n\tat org.junit.runners.ParentRunner.access$100(ParentRunner.java:66)\r\n\tat org.junit.runners.ParentRunner$2.evaluate(ParentRunner.java:293)\r\n\tat io.cucumber.junit.Cucumber$RunCucumber.evaluate(Cucumber.java:235)\r\n\tat org.junit.runners.ParentRunner$3.evaluate(ParentRunner.java:306)\r\n\tat org.junit.runners.ParentRunner.run(ParentRunner.java:413)\r\n\tat org.junit.runner.JUnitCore.run(JUnitCore.java:137)\r\n\tat com.intellij.junit4.JUnit4IdeaTestRunner.startRunnerWithArgs(JUnit4IdeaTestRunner.java:69)\r\n\tat com.intellij.rt.junit.IdeaTestRunner$Repeater.startRunnerWithArgs(IdeaTestRunner.java:33)\r\n\tat com.intellij.rt.junit.JUnitStarter.prepareStreamsAndStart(JUnitStarter.java:235)\r\n\tat com.intellij.rt.junit.JUnitStarter.main(JUnitStarter.java:54)\r\nCaused by: java.lang.reflect.InvocationTargetException\r\n\tat java.base/jdk.internal.reflect.NativeConstructorAccessorImpl.newInstance0(Native Method)\r\n\tat java.base/jdk.internal.reflect.NativeConstructorAccessorImpl.newInstance(NativeConstructorAccessorImpl.java:62)\r\n\tat java.base/jdk.internal.reflect.DelegatingConstructorAccessorImpl.newInstance(DelegatingConstructorAccessorImpl.java:45)\r\n\tat java.base/java.lang.reflect.Constructor.newInstance(Constructor.java:490)\r\n\tat io.cucumber.core.runtime.ObjectFactoryServiceLoader$DefaultJavaObjectFactory.cacheNewInstance(ObjectFactoryServiceLoader.java:141)\r\n\t... 36 more\r\nCaused by: java.lang.NoClassDefFoundError: Could not initialize class io.github.bonigarcia.wdm.WebDriverManager\r\n\tat utilities.Driver.getDriver(Driver.java:17)\r\n\tat pages.LoginPage.\u003cinit\u003e(LoginPage.java:9)\r\n\tat stepdefinitions.Day19_Login_Step_Definitions.\u003cinit\u003e(Day19_Login_Step_Definitions.java:15)\r\n\t... 41 more\r\n",
              "duration": 1023700,
              "status": "failed"
            },
            "line": 27,
            "name": "user is on the application page",
            "match": {
              "location": "stepdefinitions.Day19_Login_Step_Definitions.user_is_on_the_application_page()"
            },
            "keyword": "Given "
          },
          {
            "result": {
              "status": "skipped"
            },
            "line": 28,
            "name": "user enters manager id \"admin\"",
            "match": {
              "arguments": [
                {
                  "val": "\"admin\"",
                  "offset": 23
                }
              ],
              "location": "stepdefinitions.Day19_Login_Step_Definitions.user_enters_manager_id(java.lang.String)"
            },
            "keyword": "And "
          },
          {
            "result": {
              "status": "skipped"
            },
            "line": 29,
            "name": "user enters manager password \"Techproed123!\"",
            "match": {
              "arguments": [
                {
                  "val": "\"Techproed123!\"",
                  "offset": 29
                }
              ],
              "location": "stepdefinitions.Day19_Login_Step_Definitions.user_enters_manager_password(java.lang.String)"
            },
            "keyword": "And "
          },
          {
            "result": {
              "duration": 1999500,
              "status": "skipped"
            },
            "line": 30,
            "name": "user clicks on the login button",
            "match": {
              "location": "stepdefinitions.Day19_Login_Step_Definitions.user_clicks_on_the_login_button()"
            },
            "keyword": "When "
          },
          {
            "result": {
              "status": "skipped"
            },
            "line": 31,
            "name": "verify the \"admin\" is displayed",
            "match": {
              "arguments": [
                {
                  "val": "\"admin\"",
                  "offset": 11
                }
              ],
              "location": "stepdefinitions.Day19_Login_Step_Definitions.verify_the_is_displayed(java.lang.String)"
            },
            "keyword": "Then "
          },
          {
            "result": {
              "status": "skipped"
            },
            "line": 32,
            "name": "close the application",
            "match": {
              "location": "stepdefinitions.Day17_GoogleSearchStepDefinitions.close_the_application()"
            },
            "keyword": "Then "
          }
        ],
        "tags": [
          {
            "name": "@login_test"
          },
          {
            "name": "@admin_login_test"
          }
        ]
      }
    ],
    "name": "Login_Functionality_With_Right_Credentials",
    "description": "",
    "id": "login-functionality-with-right-credentials",
    "keyword": "Feature",
    "uri": "file:src/test/resources/features/S21.08.Eagles/US100450_user_should_login_using_manager_credentials.feature",
    "tags": [
      {
        "name": "@login_test",
        "type": "Tag",
        "location": {
          "line": 1,
          "column": 1
        }
      }
    ]
  }
]